eagerx_gui/__init__.py
eagerx_gui/configuration.py
eagerx_gui/gui.py
eagerx_gui/gui_node.py
eagerx_gui/gui_terminal.py
eagerx_gui/gui_view.py
eagerx_gui/pyqtgraph_utils.py
eagerx_gui/utils.py
eagerx_gui-0.2.15.dist-info/LICENSE
eagerx_gui-0.2.15.dist-info/METADATA
eagerx_gui-0.2.15.dist-info/WHEEL
eagerx_gui-0.2.15.dist-info/RECORD
