Metadata-Version: 2.1
Name: eagerx-gui
Version: 0.2.15
Summary: GUI to visualise graphs in EAGERx.
Home-page: https://github.com/eager-dev/eagerx_gui
License: Apache2.0
Author: Jelle Luijkx
Author-email: j.d.luijkx@tudelft.nl
Requires-Python: >=3.8,<4.0
Classifier: License :: Other/Proprietary License
Classifier: Programming Language :: Python :: 3
Classifier: Programming Language :: Python :: 3.8
Classifier: Programming Language :: Python :: 3.9
Classifier: Programming Language :: Python :: 3.10
Classifier: Programming Language :: Python :: 3.11
Requires-Dist: PyQt6 (>6.2.3,<6.5.0)
Requires-Dist: eagerx (>=0.1.38,<0.2.0)
Requires-Dist: opencv-python (>=4.5,<5.0)
Requires-Dist: pyqt6-qt6 (>6.2.3,<6.5.0)
Requires-Dist: pyqtgraph (>=0.12.4,<0.14.0)
Project-URL: Documentation, https://eagerx.readthedocs.io/en/master/
Project-URL: Repository, https://github.com/eager-dev/eagerx_gui
